almath/__init__.py
almath/libalmath.dylib
almath-1.8.3.dist-info/LICENSE.txt
almath-1.8.3.dist-info/METADATA
almath-1.8.3.dist-info/WHEEL
almath-1.8.3.dist-info/top_level.txt
almath-1.8.3.dist-info/RECORD
