Metadata-Version: 2.1
Name: almath
Version: 1.8.3
Summary: ALMath is an optimized mathematic toolbox for robotics.
Home-page: http://doc.aldebaran.com
Author: SoftBank Robotics
Author-email: release@softbankrobotics.com
License: UNKNOWN
Keywords: naoqi softbank nao pepper romeo robot
Platform: macosx-10.12-intel
Classifier: Development Status :: 5 - Production/Stable
Classifier: Intended Audience :: Developers
Classifier: Topic :: Software Development :: Embedded Systems
Classifier: Framework :: Robot Framework :: Tool
Classifier: Programming Language :: Python :: 2
Classifier: Operating System :: MacOS :: MacOS X
Requires-Python: >=2.6, <3
Requires-Dist: qi
